yamada/__init__.py
yamada/yamada.py
yamada_mst-0.1.0.dist-info/LICENSE
yamada_mst-0.1.0.dist-info/LICENSE.txt
yamada_mst-0.1.0.dist-info/METADATA
yamada_mst-0.1.0.dist-info/WHEEL
yamada_mst-0.1.0.dist-info/top_level.txt
yamada_mst-0.1.0.dist-info/RECORD
