Metadata-Version: 2.1
Name: yamada-mst
Version: 0.1.0
Summary: Package to find all minimum spanning trees in a network graph.
Home-page: https://github.com/dakota-hawkins/yamada
Author-email: dyh0110@bu.edu
License: MIT License
License-File: LICENSE
License-File: LICENSE.txt
Requires-Dist: networkx
Requires-Dist: sortedcontainers
Requires-Dist: numpy
